{
  "md3": {
    "background": "#1a110f",
    "error": "#ffb4ab",
    "error_container": "#93000a",
    "inverse_on_surface": "#392e2b",
    "inverse_primary": "#8f4b39",
    "inverse_surface": "#f1dfda",
    "on_background": "#f1dfda",
    "on_error": "#690005",
    "on_error_container": "#ffdad6",
    "on_primary": "#561f10",
    "on_primary_container": "#ffdbd1",
    "on_primary_fixed": "#3a0b01",
    "on_primary_fixed_variant": "#723523",
    "on_secondary": "#442a23",
    "on_secondary_container": "#ffdbd1",
    "on_secondary_fixed": "#2c150f",
    "on_secondary_fixed_variant": "#5d4038",
    "on_surface": "#f1dfda",
    "on_surface_variant": "#d8c2bc",
    "on_tertiary": "#3b2f05",
    "on_tertiary_container": "#f6e1a6",
    "on_tertiary_fixed": "#231b00",
    "on_tertiary_fixed_variant": "#534619",
    "outline": "#a08c87",
    "outline_variant": "#53433f",
    "primary": "#ffb5a1",
    "primary_container": "#723523",
    "primary_fixed": "#ffdbd1",
    "primary_fixed_dim": "#ffb5a1",
    "scrim": "#000000",
    "secondary": "#e7bdb2",
    "secondary_container": "#5d4038",
    "secondary_fixed": "#ffdbd1",
    "secondary_fixed_dim": "#e7bdb2",
    "shadow": "#000000",
    "source_color": "#502519",
    "surface": "#1a110f",
    "surface_bright": "#423734",
    "surface_container": "#271d1b",
    "surface_container_high": "#322825",
    "surface_container_highest": "#3d3230",
    "surface_container_low": "#231917",
    "surface_container_lowest": "#140c0a",
    "surface_dim": "#1a110f",
    "surface_tint": "#ffb5a1",
    "surface_variant": "#53433f",
    "tertiary": "#d9c58d",
    "tertiary_container": "#534619",
    "tertiary_fixed": "#f6e1a6",
    "tertiary_fixed_dim": "#d9c58d"
  },
  "palette": {
    "error0": "#000000",
    "error10": "#410002",
    "error100": "#ffffff",
    "error15": "#540003",
    "error20": "#690005",
    "error25": "#7e0007",
    "error30": "#93000a",
    "error35": "#a80710",
    "error40": "#ba1a1a",
    "error5": "#2d0001",
    "error50": "#de3730",
    "error60": "#ff5449",
    "error70": "#ff897d",
    "error80": "#ffb4ab",
    "error90": "#ffdad6",
    "error95": "#ffedea",
    "error98": "#fff8f7",
    "error99": "#fffbff",
    "neutral0": "#000000",
    "neutral10": "#201a19",
    "neutral100": "#ffffff",
    "neutral15": "#2b2423",
    "neutral20": "#362f2d",
    "neutral25": "#413a38",
    "neutral30": "#4d4543",
    "neutral35": "#59514e",
    "neutral40": "#655c5a",
    "neutral5": "#15100e",
    "neutral50": "#7f7572",
    "neutral60": "#998e8c",
    "neutral70": "#b4a9a6",
    "neutral80": "#d0c4c1",
    "neutral90": "#ede0dd",
    "neutral95": "#fbeeeb",
    "neutral98": "#fff8f6",
    "neutral99": "#fffbff",
    "neutral_variant0": "#000000",
    "neutral_variant10": "#251915",
    "neutral_variant100": "#ffffff",
    "neutral_variant15": "#30231f",
    "neutral_variant20": "#3b2d2a",
    "neutral_variant25": "#473834",
    "neutral_variant30": "#53433f",
    "neutral_variant35": "#5f4f4b",
    "neutral_variant40": "#6c5b56",
    "neutral_variant5": "#190e0b",
    "neutral_variant50": "#85736e",
    "neutral_variant60": "#a08c87",
    "neutral_variant70": "#bca7a1",
    "neutral_variant80": "#d8c2bc",
    "neutral_variant90": "#f5ded8",
    "neutral_variant95": "#ffede8",
    "neutral_variant98": "#fff8f6",
    "neutral_variant99": "#fffbff",
    "primary0": "#000000",
    "primary10": "#3b0900",
    "primary100": "#ffffff",
    "primary15": "#4d0e00",
    "primary20": "#5e1703",
    "primary25": "#6d220c",
    "primary30": "#7c2d16",
    "primary35": "#8c3821",
    "primary40": "#9b442b",
    "primary5": "#280400",
    "primary50": "#bb5b41",
    "primary60": "#da7457",
    "primary70": "#fb8d6f",
    "primary80": "#ffb5a1",
    "primary90": "#ffdbd1",
    "primary95": "#ffede8",
    "primary98": "#fff8f6",
    "primary99": "#fffbff",
    "secondary0": "#000000",
    "secondary10": "#2c150f",
    "secondary100": "#ffffff",
    "secondary15": "#381f19",
    "secondary20": "#442a23",
    "secondary25": "#51342d",
    "secondary30": "#5d4038",
    "secondary35": "#6a4b43",
    "secondary40": "#77574e",
    "secondary5": "#200b06",
    "secondary50": "#926f66",
    "secondary60": "#ae887e",
    "secondary70": "#caa298",
    "secondary80": "#e7bdb2",
    "secondary90": "#ffdbd1",
    "secondary95": "#ffede8",
    "secondary98": "#fff8f6",
    "secondary99": "#fffbff",
    "tertiary0": "#000000",
    "tertiary10": "#231b00",
    "tertiary100": "#ffffff",
    "tertiary15": "#2f2500",
    "tertiary20": "#3b2f05",
    "tertiary25": "#473a0f",
    "tertiary30": "#534619",
    "tertiary35": "#5f5124",
    "tertiary40": "#6c5d2f",
    "tertiary5": "#171000",
    "tertiary50": "#867645",
    "tertiary60": "#a18f5c",
    "tertiary70": "#bdaa74",
    "tertiary80": "#d9c58d",
    "tertiary90": "#f6e1a6",
    "tertiary95": "#fff0c9",
    "tertiary98": "#fff8f0",
    "tertiary99": "#fffbff"
  },
  "base16": {
    "base00": "#0f0e0d",
    "base01": "#2c2922",
    "base02": "#494437",
    "base03": "#655f4c",
    "base04": "#827a61",
    "base05": "#9f9576",
    "base06": "#bbb18b",
    "base07": "#d8cca0",
    "base08": "#9a7a49",
    "base09": "#693e1c",
    "base0a": "#b69f6a",
    "base0b": "#7f5e36",
    "base0c": "#d7cb9f",
    "base0d": "#4e3018",
    "base0e": "#624d30",
    "base0f": "#3a2613"
  }
}
